{
  "name": "body-language-hi",
  "stages": [
    {
      "keyFrames": [
        {
          "moveCycles": 50,
          "values": [
            1314,
            2777,
            1814,
            2277,
            2413,
            1677,
            2047,
            2047,
            2047,
            2047,
            2013,
            2080,
            2047,
            2047,
            2063,
            2030,
            2047,
            2047,
            2047,
            2170
          ]
        },
        {
          "pauseCycles": 25,
          "moveCycles": 125,
          "values": [
            1314,
            2777,
            1814,
            2277,
            2413,
            1677,
            2047,
            2047,
            2047,
            2047,
            1847,
            2243,
            2113,
            1980,
            2063,
            2030,
            2047,
            2047,
            2047,
            1904
          ]
        },
        {
          "moveCycles": 125,
          "values": [
            1314,
            2777,
            1814,
            2277,
            2413,
            1677,
            2047,
            2047,
            2047,
            2047,
            2013,
            2080,
            2047,
            2047,
            2063,
            2030,
            2047,
            2047,
            2047,
            2170
          ]
        },
        {
          "moveCycles": 125,
          "values": [
            1480,
            2610,
            1747,
            2343,
            2147,
            1944,
            2047,
            2047,
            2047,
            2047,
            2013,
            2080,
            2047,
            2047,
            2063,
            2030,
            2047,
            2047,
            2047,
            2170
          ]
        }
      ]
    }
  ]
}
