{
  "name": "stand-ready-upright",
  "stages": [
    {
      "pGains": [
        32,
        32,
        8,
        8,
        32,
        32,
        32,
        32,
        32,
        32,
        32,
        32,
        32,
        32,
        32,
        32,
        32,
        32,
        32,
        32
      ],
      "keyFrames": [
        {
          "moveCycles": 125,
          "values": [
            1498,
            2518,
            1845,
            2248,
            2381,
            1712,
            2048,
            2048,
            2052,
            2044,
            1637,
            2459,
            2653,
            1443,
            2389,
            1707,
            2057,
            2039,
            2048,
            2161
          ]
        }
      ]
    }
  ]
}
